hw2/__init__.py
hw2/task_1.py
hw2/task_2.py
hw2/task_3.py
hw_2_firepancake-0.1.2.dist-info/METADATA
hw_2_firepancake-0.1.2.dist-info/WHEEL
hw_2_firepancake-0.1.2.dist-info/RECORD
