Metadata-Version: 2.3
Name: hw-2-firepancake
Version: 0.1.2
Summary: Simple functional LaTeX code generator (tables, figures)
License: MIT
Author: Anton Poiskov
Author-email: poiskov2016@gmail.com
Requires-Python: >=3.13
Classifier: License :: OSI Approved :: MIT License
Classifier: Programming Language :: Python :: 3
Classifier: Programming Language :: Python :: 3.13
